Metadata-Version: 2.1
Name: trashparse
Version: 0.1.1
Summary: simple tool for analyzing Windows Recycle.Bin
Home-page: https://github.com/hanasuru/TrashParse
Author: hanasuru
Author-email: faqih.insani@ymail.com
License: MIT
Download-URL: https://github.com/hanasuru/TrashParse/archive/0.1.0.tar.gz
Keywords: forensic,recycle-bin,windows
Platform: UNKNOWN
Classifier: Development Status :: 3 - Alpha
Classifier: Intended Audience :: Developers
Classifier: Topic :: Software Development :: Build Tools
Classifier: License :: OSI Approved :: MIT License
Classifier: Programming Language :: Python :: 2.7
Classifier: Programming Language :: Python :: 3
